{
     
  "features": [
    { "type": "Feature",
      "properties": {
       
        "name": "Likop",
        "Ordersize": 25
      },
      "geometry": {
        "coordinates": [
         -122.581622175974,
          47.0099879494969
        ],
        "type": "Point"
      },
      "id": "8d0801fdaf9a097d944e5c275dbfc131"
    },
      "type": "Feature",
      "properties": {
        "marker-color": "#e29c7e",
        "marker-size": "large",
     
        "name": "Midtown Surf Shop",
        "Ordersize": 25
      },
      "geometry": {
        "coordinates": [
          -122.011141,
          36.979377
        ],
        "type": "Point"
      },
      "id": "8d0801fdaf9a097d944e5c275dbfc321"
    },
    
    {
      "type": "Feature",
      "properties": {
        "marker-color": "#e29c7e",
        "marker-size": "medium",
        "marker-symbol": "shop",
        "name": "Unfurl",
        "website": "www.unfurl.com",
        "Ordersize": 10
      },
      "geometry": {
        "coordinates": [
          -123.934198,
          45.719099
        ],
        "type": "Point"
      },
      "id": "bc86ed1e1c1ffbd488b7ea6e6833ffb4"
    }
  ],
  "type": "FeatureCollection"
}
